[
    {
        "cityId": "3670353",
        "name": "Salento",
        "stateId": "3671087",
        "latitude": 4.63643,
        "longitude": -75.5674
    },
    {
        "cityId": "3671099",
        "name": "Quimbaya",
        "stateId": "3671087",
        "latitude": 4.59342,
        "longitude": -75.83758
    },
    {
        "cityId": "3672256",
        "name": "Pijao",
        "stateId": "3671087",
        "latitude": 4.33333,
        "longitude": -75.66667
    },
    {
        "cityId": "3674464",
        "name": "Montenegro",
        "stateId": "3671087",
        "latitude": 4.5,
        "longitude": -75.8
    },
    {
        "cityId": "3677011",
        "name": "La Tebaida",
        "stateId": "3671087",
        "latitude": 4.45,
        "longitude": -75.8
    },
    {
        "cityId": "3682071",
        "name": "G\u00e9nova",
        "stateId": "3671087",
        "latitude": 4.22743,
        "longitude": -75.7548
    },
    {
        "cityId": "3682475",
        "name": "Filandia",
        "stateId": "3671087",
        "latitude": 4.66667,
        "longitude": -75.63333
    },
    {
        "cityId": "3686234",
        "name": "Circasia",
        "stateId": "3671087",
        "latitude": 4.5994,
        "longitude": -75.68536
    },
    {
        "cityId": "3687965",
        "name": "Calarca",
        "stateId": "3671087",
        "latitude": 4.5,
        "longitude": -75.63333
    },
    {
        "cityId": "3689563",
        "name": "Armenia",
        "stateId": "3671087",
        "latitude": 4.53307,
        "longitude": -75.70438
    },
    {
        "cityId": "9172302",
        "name": "C\u00f3rdoba",
        "stateId": "3671087",
        "latitude": 4.38055,
        "longitude": -75.66685
    },
    {
        "cityId": "9172320",
        "name": "Buenavista",
        "stateId": "3671087",
        "latitude": 4.36646,
        "longitude": -75.74375
    }
]