[
    {
        "cityId": "449540",
        "name": "Shahrest\u0101n-e Esfar\u0101yen",
        "stateId": "6201376",
        "latitude": 37,
        "longitude": 57.55
    },
    {
        "cityId": "449541",
        "name": "Shahrest\u0101n-e Bojn\u016brd",
        "stateId": "6201376",
        "latitude": 37.83333,
        "longitude": 57.33333
    },
    {
        "cityId": "449542",
        "name": "Shahrest\u0101n-e J\u0101jarm",
        "stateId": "6201376",
        "latitude": 37.01667,
        "longitude": 56.68333
    },
    {
        "cityId": "449543",
        "name": "Shahrest\u0101n-e Sh\u012brv\u0101n",
        "stateId": "6201376",
        "latitude": 37.53333,
        "longitude": 57.9
    },
    {
        "cityId": "8620941",
        "name": "Shahrest\u0101n-e M\u0101neh va Samalq\u0101n",
        "stateId": "6201376",
        "latitude": 37.7,
        "longitude": 56.6
    },
    {
        "cityId": "8620942",
        "name": "Shahrest\u0101n-e F\u0101r\u016bj",
        "stateId": "6201376",
        "latitude": 37.21667,
        "longitude": 58.21667
    },
    {
        "cityId": "9532886",
        "name": "Garmeh",
        "stateId": "6201376",
        "latitude": 37.15,
        "longitude": 56.21667
    }
]