[
    {
        "cityId": "1150075",
        "name": "Amphoe Thung Yai",
        "stateId": "1608525",
        "latitude": 8.28708,
        "longitude": 99.37196
    },
    {
        "cityId": "1150084",
        "name": "Amphoe Thung Song",
        "stateId": "1608525",
        "latitude": 8.11757,
        "longitude": 99.66907
    },
    {
        "cityId": "1150199",
        "name": "Amphoe Tha Sala",
        "stateId": "1608525",
        "latitude": 8.69367,
        "longitude": 99.88539
    },
    {
        "cityId": "1150654",
        "name": "Amphoe Sichon",
        "stateId": "1608525",
        "latitude": 8.94981,
        "longitude": 99.81322
    },
    {
        "cityId": "1150919",
        "name": "Amphoe Ron Phibun",
        "stateId": "1608525",
        "latitude": 8.17997,
        "longitude": 99.89248
    },
    {
        "cityId": "1152419",
        "name": "Amphoe Lan Saka",
        "stateId": "1608525",
        "latitude": 8.37799,
        "longitude": 99.78328
    },
    {
        "cityId": "1152964",
        "name": "Amphoe Khanom",
        "stateId": "1608525",
        "latitude": 9.18317,
        "longitude": 99.80192
    },
    {
        "cityId": "1153685",
        "name": "Amphoe Chawang",
        "stateId": "1608525",
        "latitude": 8.46322,
        "longitude": 99.51107
    },
    {
        "cityId": "1608032",
        "name": "Amphoe Pak Phanang",
        "stateId": "1608525",
        "latitude": 8.30711,
        "longitude": 100.17361
    },
    {
        "cityId": "1608644",
        "name": "Amphoe Mueang Nakhon Si Thammarat",
        "stateId": "1608525",
        "latitude": 8.44013,
        "longitude": 99.98537
    },
    {
        "cityId": "1610621",
        "name": "Amphoe Hua Sai",
        "stateId": "1608525",
        "latitude": 8.01181,
        "longitude": 100.24614
    },
    {
        "cityId": "1611182",
        "name": "Amphoe Chian Yai",
        "stateId": "1608525",
        "latitude": 8.11719,
        "longitude": 100.15819
    },
    {
        "cityId": "1611230",
        "name": "Amphoe Cha-uat",
        "stateId": "1608525",
        "latitude": 7.95645,
        "longitude": 99.98929
    },
    {
        "cityId": "7510618",
        "name": "Amphoe Tham Phannara",
        "stateId": "1608525",
        "latitude": 8.45822,
        "longitude": 99.37718
    },
    {
        "cityId": "7510619",
        "name": "Amphoe Bang Khan",
        "stateId": "1608525",
        "latitude": 8.01208,
        "longitude": 99.48449
    },
    {
        "cityId": "7510643",
        "name": "Amphoe Phra Phrom",
        "stateId": "1608525",
        "latitude": 8.32652,
        "longitude": 99.9324
    },
    {
        "cityId": "7510644",
        "name": "Amphoe Chulabhorn",
        "stateId": "1608525",
        "latitude": 8.07591,
        "longitude": 99.85365
    },
    {
        "cityId": "7510645",
        "name": "Amphoe Na Bon",
        "stateId": "1608525",
        "latitude": 8.26976,
        "longitude": 99.55694
    },
    {
        "cityId": "7510646",
        "name": "Amphoe Chang Klang",
        "stateId": "1608525",
        "latitude": 8.35697,
        "longitude": 99.64592
    },
    {
        "cityId": "7510647",
        "name": "Amphoe Phrom Khiri",
        "stateId": "1608525",
        "latitude": 8.54242,
        "longitude": 99.79229
    },
    {
        "cityId": "7510648",
        "name": "Amphoe Nopphitam",
        "stateId": "1608525",
        "latitude": 8.75166,
        "longitude": 99.67087
    },
    {
        "cityId": "7510649",
        "name": "Amphoe Phipun",
        "stateId": "1608525",
        "latitude": 8.60289,
        "longitude": 99.59528
    },
    {
        "cityId": "7510676",
        "name": "Amphoe Chaloem Phra Kiat",
        "stateId": "1608525",
        "latitude": 8.18333,
        "longitude": 100.05
    }
]