[
    {
        "cityId": "7910463",
        "name": "Toprakkale",
        "stateId": "443183",
        "latitude": 37.05037,
        "longitude": 36.11994
    },
    {
        "cityId": "8631467",
        "name": "D\u00fczi\u00e7i \u0130l\u00e7esi",
        "stateId": "443183",
        "latitude": 37.25062,
        "longitude": 36.47051
    },
    {
        "cityId": "8631468",
        "name": "Bah\u00e7e \u0130l\u00e7esi",
        "stateId": "443183",
        "latitude": 37.20105,
        "longitude": 36.57687
    },
    {
        "cityId": "8631469",
        "name": "Hasanbeyli \u0130l\u00e7esi",
        "stateId": "443183",
        "latitude": 37.13182,
        "longitude": 36.55611
    },
    {
        "cityId": "8631470",
        "name": "Kadirli \u0130l\u00e7esi",
        "stateId": "443183",
        "latitude": 37.38406,
        "longitude": 36.10284
    },
    {
        "cityId": "8631471",
        "name": "Sumbas \u0130l\u00e7esi",
        "stateId": "443183",
        "latitude": 37.46169,
        "longitude": 36.02914
    }
]