[
    {
        "cityId": "2358700",
        "name": "Kouritenga Province",
        "stateId": "6930705",
        "latitude": 12.2,
        "longitude": -0.3
    },
    {
        "cityId": "2362006",
        "name": "Province du Boulgou",
        "stateId": "6930705",
        "latitude": 11.5,
        "longitude": -0.41667
    },
    {
        "cityId": "2597261",
        "name": "Province du Koulp\u00e9logo",
        "stateId": "6930705",
        "latitude": 11.41667,
        "longitude": 0.16667
    }
]